substrateutils/__init__.py
substrateutils/cores.py
substrateutils/helper.py
substrateutils/network.py
substrateutils/nonce.py
substrateutils/settings.py
substrateutils/trades.py
substrate_utils-1.0.24.dist-info/LICENSE
substrate_utils-1.0.24.dist-info/METADATA
substrate_utils-1.0.24.dist-info/WHEEL
substrate_utils-1.0.24.dist-info/top_level.txt
substrate_utils-1.0.24.dist-info/RECORD
