Metadata-Version: 2.1
Name: substrate-utils
Version: 1.0.24
Summary: Substrate utility library providing functionality for multi-signature trading.
Home-page: https://github.com/LocalCoinSwap/substrate-utils/
Author: Nathan Worsley
Author-email: nathan@localcoinswap.com
License: GPLv3
Platform: UNKNOWN
Classifier: License :: OSI Approved :: GNU General Public License v3 (GPLv3)
Classifier: Programming Language :: Python
Classifier: Programming Language :: Python :: 3
Classifier: Programming Language :: Python :: 3.7
Classifier: Programming Language :: Python :: 3.8
Classifier: Programming Language :: Python :: Implementation :: CPython
Classifier: Programming Language :: Python :: Implementation :: PyPy
Requires-Python: >=3.7.0
Requires-Dist: websockets (==8.1)
Requires-Dist: scalecodec (==1.0.34)
Requires-Dist: base58 (==2.0.1)
Requires-Dist: py-bip39-bindings (==0.1.6)
Requires-Dist: py-sr25519-bindings (==0.1.1)
Requires-Dist: xxhash (==1.4.3)
Provides-Extra: dev
Requires-Dist: coverage (==5.1) ; extra == 'dev'
Requires-Dist: ipython (==7.14.0) ; extra == 'dev'
Requires-Dist: portray (==1.3.1) ; extra == 'dev'
Requires-Dist: pre-commit (==2.3.0) ; extra == 'dev'
Requires-Dist: pytest (==5.4.1) ; extra == 'dev'
Requires-Dist: pytest-mock (==3.1.0) ; extra == 'dev'
